pinnacle_python/__init__.py
pinnacle_python/endpoints.py
pinnacle_python/schedules.py
pinnacle_python-0.0.3.dist-info/METADATA
pinnacle_python-0.0.3.dist-info/WHEEL
pinnacle_python-0.0.3.dist-info/RECORD
