Metadata-Version: 2.1
Name: pinnacle-python
Version: 0.0.3
Summary: 
Author: Ivan Zhang
Author-email: ivanzhangofficial@gmail.com
Requires-Python: >=3.12,<4.0
Classifier: Programming Language :: Python :: 3
Classifier: Programming Language :: Python :: 3.12
Requires-Dist: python-dotenv (>=1.0.1,<2.0.0)
Requires-Dist: schedule (>=1.2.2,<2.0.0)
